bioio_ome_zarr/__init__.py
bioio_ome_zarr/py.typed
bioio_ome_zarr/reader.py
bioio_ome_zarr/reader_metadata.py
bioio_ome_zarr/utils.py
bioio_ome_zarr/writers/__init__.py
bioio_ome_zarr/writers/config.py
bioio_ome_zarr/writers/metadata.py
bioio_ome_zarr/writers/ome_zarr_writer.py
bioio_ome_zarr/writers/ome_zarr_writer_v2.py
bioio_ome_zarr/writers/ome_zarr_writer_v3.py
bioio_ome_zarr/writers/utils.py
bioio_ome_zarr-3.2.1.dist-info/licenses/LICENSE
scripts/benchmark.py
bioio_ome_zarr-3.2.1.dist-info/METADATA
bioio_ome_zarr-3.2.1.dist-info/WHEEL
bioio_ome_zarr-3.2.1.dist-info/entry_points.txt
bioio_ome_zarr-3.2.1.dist-info/top_level.txt
bioio_ome_zarr-3.2.1.dist-info/RECORD
