Metadata-Version: 2.4
Name: bioio-ome-zarr
Version: 3.2.1
Summary: A BioIO reader plugin for reading Zarr files in the OME format.
Author-email: bioio-devs <brian.whitney@alleninstitute.org>
License: MIT License
Project-URL: Homepage, https://github.com/bioio-devs/bioio-ome-zarr
Project-URL: Bug Tracker, https://github.com/bioio-devs/bioio-ome-zarr/issues
Project-URL: User Support, https://github.com/bioio-devs/bioio-ome-zarr/issues
Classifier: Development Status :: 4 - Beta
Classifier: Natural Language :: English
Classifier: Programming Language :: Python :: 3.11
Classifier: Programming Language :: Python :: 3.12
Classifier: Programming Language :: Python :: 3.13
Requires-Python: >=3.11
License-File: LICENSE
Requires-Dist: bioio-base>=3.1.0
Requires-Dist: dask!=2025.11.0
Requires-Dist: fsspec[http]>=2022.8.0
Requires-Dist: s3fs>=2023.9.0
Requires-Dist: scikit-image!=0.23.0
Requires-Dist: xarray>=0.16.1
Requires-Dist: zarr>=3.1.0
Provides-Extra: lint
Requires-Dist: pre-commit>=2.20.0; extra == "lint"
Provides-Extra: test
Requires-Dist: coverage>=5.1; extra == "test"
Requires-Dist: ngff-zarr[validate]>=0.8.2; extra == "test"
Requires-Dist: pytest>=5.4.3; extra == "test"
Requires-Dist: pytest-cov>=2.9.0; extra == "test"
Requires-Dist: pytest-raises>=0.11; extra == "test"
Requires-Dist: ome-zarr-models>=1.4; extra == "test"
Dynamic: license-file
